libervia/VERSION
libervia/__init__.py
libervia/common/__init__.py
libervia/common/constants.py
libervia/pages/app/page_meta.py
libervia/pages/blog/page_meta.py
libervia/pages/blog/view/page_meta.py
libervia/pages/blog/view/atom.xml/page_meta.py
libervia/pages/chat/page_meta.py
libervia/pages/chat/select/page_meta.py
libervia/pages/events/page_meta.py
libervia/pages/events/admin/page_meta.py
libervia/pages/events/new/page_meta.py
libervia/pages/events/rsvp/page_meta.py
libervia/pages/events/view/page_meta.py
libervia/pages/files/page_meta.py
libervia/pages/files/list/page_meta.py
libervia/pages/files/view/page_meta.py
libervia/pages/forums/page_meta.py
libervia/pages/forums/list/page_meta.py
libervia/pages/forums/topics/page_meta.py
libervia/pages/forums/view/page_meta.py
libervia/pages/g/page_meta.py
libervia/pages/g/e/page_meta.py
libervia/pages/login/page_meta.py
libervia/pages/login/logged/page_meta.py
libervia/pages/merge-requests/page_meta.py
libervia/pages/merge-requests/disco/page_meta.py
libervia/pages/merge-requests/edit/page_meta.py
libervia/pages/merge-requests/new/page_meta.py
libervia/pages/merge-requests/view/page_meta.py
libervia/pages/photos/page_meta.py
libervia/pages/photos/album/page_meta.py
libervia/pages/register/page_meta.py
libervia/pages/tickets/page_meta.py
libervia/pages/tickets/disco/page_meta.py
libervia/pages/tickets/edit/page_meta.py
libervia/pages/tickets/new/page_meta.py
libervia/pages/tickets/view/page_meta.py
libervia/pages/u/page_meta.py
libervia/pages/u/atom.xml/page_meta.py
libervia/pages/u/blog/page_meta.py
libervia/server/__init__.py
libervia/server/blog.py
libervia/server/classes.py
libervia/server/constants.py
libervia/server/html_tools.py
libervia/server/pages.py
libervia/server/pages_tools.py
libervia/server/server.py
libervia/server/session_iface.py
libervia/server/tasks.py
libervia/server/utils.py
libervia/server/websockets.py
libervia-0.7.0.data/data/share/doc/libervia/COPYING
libervia-0.7.0.dist-info/COPYING
libervia-0.7.0.dist-info/METADATA
libervia-0.7.0.dist-info/WHEEL
libervia-0.7.0.dist-info/top_level.txt
libervia-0.7.0.dist-info/RECORD
