Metadata-Version: 2.1
Name: libervia
Version: 0.7.0
Summary: Web frontend for Salut à Toi
Home-page: https://www.salut-a-toi.org
Author: Association « Salut à Toi »
Author-email: contact@goffi.org
License: UNKNOWN
Platform: UNKNOWN
Classifier: Development Status :: 3 - Alpha
Classifier: Environment :: Web Environment
Classifier: Framework :: Twisted
Classifier: License :: OSI Approved :: GNU Affero General Public License v3 or later (AGPLv3+)
Classifier: Operating System :: POSIX :: Linux
Classifier: Topic :: Communications :: Chat
Requires-Python: ~=2.7
Requires-Dist: sat (>=0.7.0)
Requires-Dist: sat-templates
Requires-Dist: twisted
Requires-Dist: txJSON-RPC (==0.3.1)
Requires-Dist: zope.interface
Requires-Dist: pyopenssl
Requires-Dist: jinja2 (>=2.9)
Requires-Dist: shortuuid
Requires-Dist: autobahn
